{
  "image": {
    "sha256": "1897476a1005c775b0796151c5c0350c70d1e9ac925caa4d691e1f37f29aadb4"
  },
  "node-name": "imu_transformer_node",
  "package": {
    "name": "imu_transformer",
    "path": "/ros_ws/src/imu_pipeline/imu_transformer"
  },
  "sources": [
    "/ros_ws/src/imu_pipeline/imu_transformer/src/imu_transformer_node.cpp"
  ],
  "program": {
    "program": {
      "entrypoint": "main",
      "functions": [
        {
          "name": "main",
          "parameters": [
            {
              "index": 0,
              "name": "argc",
              "type": "integer"
            }
          ],
          "body": {
            "kind": "compound",
            "statements": [
              {
                "kind": "ros-init",
                "name": {
                  "kind": "string-literal",
                  "literal": "imu_transformer"
                }
              },
              {
                "kind": "ros-init",
                "name": {
                  "kind": "string-literal",
                  "literal": "imu_transformer"
                }
              }
            ]
          }
        }
      ]
    }
  }
}