{"package": "lane_planner", "node": "lane_rule", "periodic_behavior": [], "reactive_behavior": [{"publisher": {"variable": "traffic_pub", "topic": "/traffic_waypoints_array"}, "subscriber": {"callback": "(anonymous namespace)::cache_node", "topic": "/vector_map_info/node"}}, {"publisher": {"variable": "traffic_pub", "topic": "/traffic_waypoints_array"}, "subscriber": {"callback": "(anonymous namespace)::cache_dtlane", "topic": "/vector_map_info/dtlane"}}, {"publisher": {"variable": "traffic_pub", "topic": "/traffic_waypoints_array"}, "subscriber": {"callback": "(anonymous namespace)::cache_point", "topic": "/vector_map_info/point_class"}}, {"publisher": {"variable": "traffic_pub", "topic": "/traffic_waypoints_array"}, "subscriber": {"callback": "(anonymous namespace)::create_waypoint", "topic": "/lane_waypoints_array"}}, {"publisher": {"variable": "traffic_pub", "topic": "/traffic_waypoints_array"}, "subscriber": {"callback": "(anonymous namespace)::cache_lane", "topic": "/vector_map_info/lane"}}, {"publisher": {"variable": "traffic_pub", "topic": "/traffic_waypoints_array"}, "subscriber": {"callback": "(anonymous namespace)::cache_stopline", "topic": "/vector_map_info/stop_line"}}, {"publisher": {"variable": "traffic_pub", "topic": "/traffic_waypoints_array"}, "subscriber": {"callback": "(anonymous namespace)::cache_node", "topic": "/vector_map_info/node"}}, {"publisher": {"variable": "traffic_pub", "topic": "/traffic_waypoints_array"}, "subscriber": {"callback": "(anonymous namespace)::cache_dtlane", "topic": "/vector_map_info/dtlane"}}, {"publisher": {"variable": "traffic_pub", "topic": "/traffic_waypoints_array"}, "subscriber": {"callback": "(anonymous namespace)::cache_point", "topic": "/vector_map_info/point_class"}}, {"publisher": {"variable": "traffic_pub", "topic": "/traffic_waypoints_array"}, "subscriber": {"callback": "(anonymous namespace)::create_waypoint", "topic": "/lane_waypoints_array"}}, {"publisher": {"variable": "traffic_pub", "topic": "/traffic_waypoints_array"}, "subscriber": {"callback": "(anonymous namespace)::cache_lane", "topic": "/vector_map_info/lane"}}, {"publisher": {"variable": "traffic_pub", "topic": "/traffic_waypoints_array"}, "subscriber": {"callback": "(anonymous namespace)::cache_stopline", "topic": "/vector_map_info/stop_line"}}, {"publisher": {"variable": "red_pub", "topic": "/red_waypoints_array"}, "subscriber": {"callback": "(anonymous namespace)::cache_node", "topic": "/vector_map_info/node"}}, {"publisher": {"variable": "red_pub", "topic": "/red_waypoints_array"}, "subscriber": {"callback": "(anonymous namespace)::cache_dtlane", "topic": "/vector_map_info/dtlane"}}, {"publisher": {"variable": "red_pub", "topic": "/red_waypoints_array"}, "subscriber": {"callback": "(anonymous namespace)::cache_point", "topic": "/vector_map_info/point_class"}}, {"publisher": {"variable": "red_pub", "topic": "/red_waypoints_array"}, "subscriber": {"callback": "(anonymous namespace)::create_waypoint", "topic": "/lane_waypoints_array"}}, {"publisher": {"variable": "red_pub", "topic": "/red_waypoints_array"}, "subscriber": {"callback": "(anonymous namespace)::cache_lane", "topic": "/vector_map_info/lane"}}, {"publisher": {"variable": "red_pub", "topic": "/red_waypoints_array"}, "subscriber": {"callback": "(anonymous namespace)::cache_stopline", "topic": "/vector_map_info/stop_line"}}, {"publisher": {"variable": "green_pub", "topic": "/green_waypoints_array"}, "subscriber": {"callback": "(anonymous namespace)::cache_node", "topic": "/vector_map_info/node"}}, {"publisher": {"variable": "green_pub", "topic": "/green_waypoints_array"}, "subscriber": {"callback": "(anonymous namespace)::cache_dtlane", "topic": "/vector_map_info/dtlane"}}, {"publisher": {"variable": "green_pub", "topic": "/green_waypoints_array"}, "subscriber": {"callback": "(anonymous namespace)::cache_point", "topic": "/vector_map_info/point_class"}}, {"publisher": {"variable": "green_pub", "topic": "/green_waypoints_array"}, "subscriber": {"callback": "(anonymous namespace)::create_waypoint", "topic": "/lane_waypoints_array"}}, {"publisher": {"variable": "green_pub", "topic": "/green_waypoints_array"}, "subscriber": {"callback": "(anonymous namespace)::cache_lane", "topic": "/vector_map_info/lane"}}, {"publisher": {"variable": "green_pub", "topic": "/green_waypoints_array"}, "subscriber": {"callback": "(anonymous namespace)::cache_stopline", "topic": "/vector_map_info/stop_line"}}], "potential_state_vars": [], "transitions": [], "unclassified_publish": []}