{
  "image": {
    "sha256": "d83c3ddd4d4c58ff8f16d9a9e57b33604218b4637fa55b70e25a594c1acdf466"
  },
  "node-name": "lane_navi",
  "package": {
    "name": "lane_planner",
    "path": "/home/autoware/Autoware/ros/src/computing/planning/mission/packages/lane_planner"
  },
  "sources": [
    "/home/autoware/Autoware/ros/src/computing/planning/mission/packages/lane_planner/nodes/lane_navi/lane_navi.cpp"
  ],
  "program": {
    "program": {
      "entrypoint": "main",
      "functions": [
        {
          "name": "main",
          "parameters": [
            {
              "index": 0,
              "name": "argc",
              "type": "integer"
            }
          ],
          "body": {
            "kind": "compound",
            "statements": [
              {
                "kind": "ros-init",
                "name": {
                  "kind": "string-literal",
                  "literal": "lane_navi"
                }
              },
              {
                "kind": "assignment",
                "variable": "v0",
                "value": {
                  "kind": "reads-param-with-default",
                  "name": {
                    "kind": "concatenate",
                    "lhs": {
                      "kind": "node-handle",
                      "namespace": {
                        "kind": "string-literal",
                        "literal": ""
                      }
                    },
                    "rhs": {
                      "kind": "string-literal",
                      "literal": "/lane_navi/sub_vmap_queue_size"
                    }
                  },
                  "default": {
                    "kind": "unknown"
                  }
                }
              },
              {
                "kind": "assignment",
                "variable": "v1",
                "value": {
                  "kind": "reads-param-with-default",
                  "name": {
                    "kind": "concatenate",
                    "lhs": {
                      "kind": "node-handle",
                      "namespace": {
                        "kind": "string-literal",
                        "literal": ""
                      }
                    },
                    "rhs": {
                      "kind": "string-literal",
                      "literal": "/lane_navi/sub_route_queue_size"
                    }
                  },
                  "default": {
                    "kind": "unknown"
                  }
                }
              },
              {
                "kind": "assignment",
                "variable": "v2",
                "value": {
                  "kind": "reads-param-with-default",
                  "name": {
                    "kind": "concatenate",
                    "lhs": {
                      "kind": "node-handle",
                      "namespace": {
                        "kind": "string-literal",
                        "literal": ""
                      }
                    },
                    "rhs": {
                      "kind": "string-literal",
                      "literal": "/lane_navi/pub_waypoint_queue_size"
                    }
                  },
                  "default": {
                    "kind": "unknown"
                  }
                }
              },
              {
                "kind": "assignment",
                "variable": "v3",
                "value": {
                  "kind": "reads-param-with-default",
                  "name": {
                    "kind": "concatenate",
                    "lhs": {
                      "kind": "node-handle",
                      "namespace": {
                        "kind": "string-literal",
                        "literal": ""
                      }
                    },
                    "rhs": {
                      "kind": "string-literal",
                      "literal": "/lane_navi/pub_waypoint_latch"
                    }
                  },
                  "default": {
                    "kind": "unknown"
                  }
                }
              },
              {
                "kind": "assignment",
                "variable": "v4",
                "value": {
                  "kind": "reads-param-with-default",
                  "name": {
                    "kind": "concatenate",
                    "lhs": {
                      "kind": "node-handle",
                      "namespace": {
                        "kind": "string-literal",
                        "literal": ""
                      }
                    },
                    "rhs": {
                      "kind": "string-literal",
                      "literal": "/lane_navi/waypoint_max"
                    }
                  },
                  "default": {
                    "kind": "unknown"
                  }
                }
              },
              {
                "kind": "assignment",
                "variable": "v5",
                "value": {
                  "kind": "reads-param-with-default",
                  "name": {
                    "kind": "concatenate",
                    "lhs": {
                      "kind": "node-handle",
                      "namespace": {
                        "kind": "string-literal",
                        "literal": ""
                      }
                    },
                    "rhs": {
                      "kind": "string-literal",
                      "literal": "/lane_navi/search_radius"
                    }
                  },
                  "default": {
                    "kind": "unknown"
                  }
                }
              },
              {
                "kind": "assignment",
                "variable": "v6",
                "value": {
                  "kind": "reads-param-with-default",
                  "name": {
                    "kind": "concatenate",
                    "lhs": {
                      "kind": "node-handle",
                      "namespace": {
                        "kind": "string-literal",
                        "literal": ""
                      }
                    },
                    "rhs": {
                      "kind": "string-literal",
                      "literal": "/lane_navi/velocity"
                    }
                  },
                  "default": {
                    "kind": "unknown"
                  }
                }
              },
              {
                "kind": "assignment",
                "variable": "v7",
                "value": {
                  "kind": "reads-param-with-default",
                  "name": {
                    "kind": "concatenate",
                    "lhs": {
                      "kind": "node-handle",
                      "namespace": {
                        "kind": "string-literal",
                        "literal": ""
                      }
                    },
                    "rhs": {
                      "kind": "string-literal",
                      "literal": "/lane_navi/frame_id"
                    }
                  },
                  "default": {
                    "kind": "unknown"
                  }
                }
              },
              {
                "kind": "assignment",
                "variable": "v8",
                "value": {
                  "kind": "reads-param-with-default",
                  "name": {
                    "kind": "concatenate",
                    "lhs": {
                      "kind": "node-handle",
                      "namespace": {
                        "kind": "string-literal",
                        "literal": ""
                      }
                    },
                    "rhs": {
                      "kind": "string-literal",
                      "literal": "/lane_navi/output_file"
                    }
                  },
                  "default": {
                    "kind": "unknown"
                  }
                }
              },
              {
                "kind": "publishes-to",
                "name": {
                  "kind": "concatenate",
                  "lhs": {
                    "kind": "node-handle",
                    "namespace": {
                      "kind": "string-literal",
                      "literal": ""
                    }
                  },
                  "rhs": {
                    "kind": "string-literal",
                    "literal": "/lane_waypoints_array"
                  }
                },
                "format": "autoware_msgs/LaneArray"
              },
              {
                "kind": "subscribes-to",
                "name": {
                  "kind": "concatenate",
                  "lhs": {
                    "kind": "node-handle",
                    "namespace": {
                      "kind": "string-literal",
                      "literal": ""
                    }
                  },
                  "rhs": {
                    "kind": "string-literal",
                    "literal": "/route_cmd"
                  }
                },
                "format": "tablet_socket_msgs/route_cmd"
              },
              {
                "kind": "subscribes-to",
                "name": {
                  "kind": "concatenate",
                  "lhs": {
                    "kind": "node-handle",
                    "namespace": {
                      "kind": "string-literal",
                      "literal": ""
                    }
                  },
                  "rhs": {
                    "kind": "string-literal",
                    "literal": "/vector_map_info/point"
                  }
                },
                "format": "vector_map_msgs/PointArray"
              },
              {
                "kind": "subscribes-to",
                "name": {
                  "kind": "concatenate",
                  "lhs": {
                    "kind": "node-handle",
                    "namespace": {
                      "kind": "string-literal",
                      "literal": ""
                    }
                  },
                  "rhs": {
                    "kind": "string-literal",
                    "literal": "/vector_map_info/lane"
                  }
                },
                "format": "vector_map_msgs/LaneArray"
              },
              {
                "kind": "subscribes-to",
                "name": {
                  "kind": "concatenate",
                  "lhs": {
                    "kind": "node-handle",
                    "namespace": {
                      "kind": "string-literal",
                      "literal": ""
                    }
                  },
                  "rhs": {
                    "kind": "string-literal",
                    "literal": "/vector_map_info/node"
                  }
                },
                "format": "vector_map_msgs/NodeArray"
              }
            ]
          }
        }
      ]
    }
  }
}