{"package": "map_file", "node": "points_map_loader", "periodic_behavior": [], "reactive_behavior": [{"publisher": {"variable": "pcd_pub"}, "subscriber": {"callback": "(anonymous namespace)::publish_gnss_pcd"}}, {"publisher": {"variable": "pcd_pub"}, "subscriber": {"callback": "(anonymous namespace)::publish_dragged_pcd"}}, {"publisher": {"variable": "pcd_pub"}, "subscriber": {"callback": "(anonymous namespace)::publish_current_pcd"}}, {"publisher": {"variable": "stat_pub"}, "subscriber": {"callback": "(anonymous namespace)::publish_gnss_pcd"}}, {"publisher": {"variable": "stat_pub"}, "subscriber": {"callback": "(anonymous namespace)::publish_dragged_pcd"}}, {"publisher": {"variable": "stat_pub"}, "subscriber": {"callback": "(anonymous namespace)::publish_current_pcd"}}, {"publisher": {"variable": "stat_pub"}, "event": "component-init"}, {"publisher": {"variable": "pcd_pub"}, "event": "component-init"}, {"publisher": {"variable": "stat_pub"}, "event": "component-init"}], "potential_state_vars": [], "transitions": [{"type": "message", "condition": "pcd.sensor_msgs::PointCloud2_<std::allocator<void>>::width != 0", "callback": "(anonymous namespace)::publish_gnss_pcd", "state_changes": [], "outputs": [{"publisher": {"variable": "pcd_pub"}}, {"publisher": {"variable": "stat_pub"}}]}, {"type": "message", "condition": "pcd.sensor_msgs::PointCloud2_<std::allocator<void>>::width != 0", "callback": "(anonymous namespace)::publish_dragged_pcd", "state_changes": [], "outputs": [{"publisher": {"variable": "pcd_pub"}}, {"publisher": {"variable": "stat_pub"}}]}, {"type": "message", "condition": "pcd.sensor_msgs::PointCloud2_<std::allocator<void>>::width != 0", "callback": "(anonymous namespace)::publish_current_pcd", "state_changes": [], "outputs": [{"publisher": {"variable": "pcd_pub"}}, {"publisher": {"variable": "stat_pub"}}]}], "unclassified_publish": []}